MANIFEST.in
setup.py
aomi/__init__.py
aomi/__main__.py
aomi/cli.py
aomi/error.py
aomi/exceptions.py
aomi/filez.py
aomi/helpers.py
aomi/render.py
aomi/seed_action.py
aomi/template.py
aomi/util.py
aomi/validation.py
aomi/vault.py
aomi/version
aomi.egg-info/PKG-INFO
aomi.egg-info/SOURCES.txt
aomi.egg-info/dependency_links.txt
aomi.egg-info/entry_points.txt
aomi.egg-info/requires.txt
aomi.egg-info/top_level.txt
aomi/model/__init__.py
aomi/model/auth.py
aomi/model/aws.py
aomi/model/backend.py
aomi/model/context.py
aomi/model/generic.py
aomi/model/resource.py
aomi/model/ssh.py
aomi/templates/aws-credentials-help.yml
aomi/templates/aws-credentials.j2
aomi/templates/bundle-config-help.yml
aomi/templates/bundle-config.j2
aomi/templates/docker-auth-help.yml
aomi/templates/docker-auth.j2
aomi/templates/gem-credentials-help.yml
aomi/templates/gem-credentials.j2
aomi/templates/json-kv-help.yml
aomi/templates/json-kv.j2
aomi/templates/pip-conf-help.yml
aomi/templates/pip-conf.j2
aomi/templates/pypirc-help.yml
aomi/templates/pypirc.j2
aomi/templates/shenv-help.yml
aomi/templates/shenv.j2
aomi/templates/terraform-aws-help.yml
aomi/templates/terraform-aws.j2
aomi/templates/tfvars-help.yml
aomi/templates/tfvars.j2
aomi/templates/yaml-kv-help.yml
aomi/templates/yaml-kv.j2
aomi/words/academic.txt
aomi/words/animals.txt