Metadata-Version: 1.0
Name: aomi
Version: 1.9.0
Summary: Easy access to secrets is not as bad as it sounds
Home-page: https://github.com/autodesk/aomi
Author: Jonathan Freedman
Author-email: jonathan.freedman@autodesk.com
License: MIT
Platform: UNKNOWN
